<!DOCTYPE codename-engine-character>
<character y="150" sprite="phase3" icon="phase3" color="#AE66CE" holdTime="6.1">
	<anim name="idle" anim="Phase3 idle0" x="0" y="0" fps="14" loop="true"/>
	<anim name="singUP" anim="Phase3 up0" x="0" y="0" fps="14" loop="false"/>
	<anim name="singLEFT" anim="Phase3 left0" x="0" y="0" fps="14" loop="false"/>
	<anim name="singRIGHT" anim="Phase3 right0" x="0" y="0" fps="14" loop="false"/>
	<anim name="singDOWN" anim="Phase3 down0" x="0" y="0" fps="14" loop="false"/>
	<anim name="idle" anim="Phase3 idle0" x="0" y="0" fps="14" loop="true"/>
	<anim name="singDOWN" anim="Phase3 down0" x="0" y="0" fps="14" loop="false"/>
	<anim name="singUP" anim="Phase3 up0" x="0" y="0" fps="14" loop="false"/>
	<anim name="singLEFT" anim="Phase3 left0" x="0" y="0" fps="14" loop="false"/>
	<anim name="singRIGHT" anim="Phase3 right0" x="0" y="0" fps="14" loop="false"/>
</character>
